make_vcard/__init__.py
make_vcard/__main__.py
make_vcard/command.py
make_vcard/generate_vcard.py
make_vcard/globals.py
make_vcard/read_file.py
make_vcard-0.1.5.dist-info/METADATA
make_vcard-0.1.5.dist-info/WHEEL
make_vcard-0.1.5.dist-info/top_level.txt
make_vcard-0.1.5.dist-info/RECORD
