Metadata-Version: 2.1
Name: make-vcard
Version: 0.1.5
Summary: 用于以execl文件生成.vcf通讯录导入文件
Home-page: https://gitee.com/antianshi/make_vcard
Author: antianshi
Author-email: 948258209@qq.com
License: UNKNOWN
Platform: UNKNOWN
Classifier: Programming Language :: Python :: 3
Classifier: License :: OSI Approved :: MIT License
Classifier: Operating System :: OS Independent
Requires-Dist: openpyxl (>=3.0.9)
